<?xml version="1.0" encoding="utf-8" standalone="yes"?>
<Gesture Name = "triangle">
	<Stroke>
		<Point X = "429" Y = "-124" T = "0" Pressure = "0" />
		<Point X = "432" Y = "-124" T = "0" Pressure = "0" />
		<Point X = "432" Y = "-124" T = "0" Pressure = "0" />
		<Point X = "432" Y = "-126" T = "0" Pressure = "0" />
		<Point X = "433" Y = "-127" T = "0" Pressure = "0" />
		<Point X = "435" Y = "-132" T = "0" Pressure = "0" />
		<Point X = "439" Y = "-136" T = "0" Pressure = "0" />
		<Point X = "439" Y = "-136" T = "0" Pressure = "0" />
		<Point X = "444" Y = "-142" T = "0" Pressure = "0" />
		<Point X = "451" Y = "-150" T = "0" Pressure = "0" />
		<Point X = "460" Y = "-159" T = "0" Pressure = "0" />
		<Point X = "472" Y = "-169" T = "0" Pressure = "0" />
		<Point X = "487" Y = "-184" T = "0" Pressure = "0" />
		<Point X = "487" Y = "-184" T = "0" Pressure = "0" />
		<Point X = "501" Y = "-199" T = "0" Pressure = "0" />
		<Point X = "516" Y = "-213" T = "0" Pressure = "0" />
		<Point X = "528" Y = "-228" T = "0" Pressure = "0" />
		<Point X = "540" Y = "-240" T = "0" Pressure = "0" />
		<Point X = "540" Y = "-240" T = "0" Pressure = "0" />
		<Point X = "550" Y = "-250" T = "0" Pressure = "0" />
		<Point X = "567" Y = "-264" T = "0" Pressure = "0" />
		<Point X = "582" Y = "-274" T = "0" Pressure = "0" />
		<Point X = "582" Y = "-274" T = "0" Pressure = "0" />
		<Point X = "588" Y = "-277" T = "0" Pressure = "0" />
		<Point X = "592" Y = "-280" T = "0" Pressure = "0" />
		<Point X = "597" Y = "-283" T = "0" Pressure = "0" />
		<Point X = "597" Y = "-283" T = "0" Pressure = "0" />
		<Point X = "601" Y = "-288" T = "0" Pressure = "0" />
		<Point X = "604" Y = "-289" T = "0" Pressure = "0" />
		<Point X = "606" Y = "-291" T = "0" Pressure = "0" />
		<Point X = "606" Y = "-291" T = "0" Pressure = "0" />
		<Point X = "606" Y = "-291" T = "0" Pressure = "0" />
		<Point X = "606" Y = "-291" T = "0" Pressure = "0" />
		<Point X = "606" Y = "-291" T = "0" Pressure = "0" />
		<Point X = "606" Y = "-291" T = "0" Pressure = "0" />
		<Point X = "606" Y = "-291" T = "0" Pressure = "0" />
		<Point X = "606" Y = "-291" T = "0" Pressure = "0" />
		<Point X = "606" Y = "-291" T = "0" Pressure = "0" />
		<Point X = "606" Y = "-291" T = "0" Pressure = "0" />
		<Point X = "606" Y = "-291" T = "0" Pressure = "0" />
		<Point X = "606" Y = "-291" T = "0" Pressure = "0" />
		<Point X = "606" Y = "-291" T = "0" Pressure = "0" />
		<Point X = "606" Y = "-291" T = "0" Pressure = "0" />
		<Point X = "606" Y = "-291" T = "0" Pressure = "0" />
		<Point X = "606" Y = "-291" T = "0" Pressure = "0" />
		<Point X = "606" Y = "-291" T = "0" Pressure = "0" />
		<Point X = "606" Y = "-291" T = "0" Pressure = "0" />
		<Point X = "605" Y = "-290" T = "0" Pressure = "0" />
		<Point X = "603" Y = "-290" T = "0" Pressure = "0" />
		<Point X = "603" Y = "-288" T = "0" Pressure = "0" />
		<Point X = "603" Y = "-288" T = "0" Pressure = "0" />
		<Point X = "600" Y = "-288" T = "0" Pressure = "0" />
		<Point X = "597" Y = "-287" T = "0" Pressure = "0" />
		<Point X = "593" Y = "-284" T = "0" Pressure = "0" />
		<Point X = "593" Y = "-284" T = "0" Pressure = "0" />
		<Point X = "585" Y = "-281" T = "0" Pressure = "0" />
		<Point X = "579" Y = "-279" T = "0" Pressure = "0" />
		<Point X = "570" Y = "-275" T = "0" Pressure = "0" />
		<Point X = "561" Y = "-272" T = "0" Pressure = "0" />
		<Point X = "561" Y = "-272" T = "0" Pressure = "0" />
		<Point X = "548" Y = "-266" T = "0" Pressure = "0" />
		<Point X = "536" Y = "-263" T = "0" Pressure = "0" />
		<Point X = "519" Y = "-257" T = "0" Pressure = "0" />
		<Point X = "519" Y = "-257" T = "0" Pressure = "0" />
		<Point X = "506" Y = "-251" T = "0" Pressure = "0" />
		<Point X = "491" Y = "-243" T = "0" Pressure = "0" />
		<Point X = "477" Y = "-237" T = "0" Pressure = "0" />
		<Point X = "477" Y = "-237" T = "0" Pressure = "0" />
		<Point X = "464" Y = "-233" T = "0" Pressure = "0" />
		<Point X = "450" Y = "-225" T = "0" Pressure = "0" />
		<Point X = "435" Y = "-219" T = "0" Pressure = "0" />
		<Point X = "408" Y = "-207" T = "0" Pressure = "0" />
		<Point X = "393" Y = "-201" T = "0" Pressure = "0" />
		<Point X = "393" Y = "-201" T = "0" Pressure = "0" />
		<Point X = "381" Y = "-197" T = "0" Pressure = "0" />
		<Point X = "369" Y = "-191" T = "0" Pressure = "0" />
		<Point X = "360" Y = "-186" T = "0" Pressure = "0" />
		<Point X = "360" Y = "-186" T = "0" Pressure = "0" />
		<Point X = "353" Y = "-183" T = "0" Pressure = "0" />
		<Point X = "347" Y = "-180" T = "0" Pressure = "0" />
		<Point X = "344" Y = "-179" T = "0" Pressure = "0" />
		<Point X = "342" Y = "-179" T = "0" Pressure = "0" />
		<Point X = "342" Y = "-179" T = "0" Pressure = "0" />
		<Point X = "342" Y = "-179" T = "0" Pressure = "0" />
		<Point X = "342" Y = "-179" T = "0" Pressure = "0" />
		<Point X = "342" Y = "-179" T = "0" Pressure = "0" />
		<Point X = "342" Y = "-179" T = "0" Pressure = "0" />
		<Point X = "342" Y = "-179" T = "0" Pressure = "0" />
		<Point X = "342" Y = "-179" T = "0" Pressure = "0" />
		<Point X = "342" Y = "-179" T = "0" Pressure = "0" />
		<Point X = "342" Y = "-179" T = "0" Pressure = "0" />
		<Point X = "342" Y = "-179" T = "0" Pressure = "0" />
		<Point X = "342" Y = "-179" T = "0" Pressure = "0" />
		<Point X = "342" Y = "-179" T = "0" Pressure = "0" />
		<Point X = "342" Y = "-179" T = "0" Pressure = "0" />
		<Point X = "342" Y = "-179" T = "0" Pressure = "0" />
		<Point X = "342" Y = "-179" T = "0" Pressure = "0" />
		<Point X = "342" Y = "-179" T = "0" Pressure = "0" />
		<Point X = "342" Y = "-177" T = "0" Pressure = "0" />
		<Point X = "343" Y = "-177" T = "0" Pressure = "0" />
		<Point X = "348" Y = "-174" T = "0" Pressure = "0" />
		<Point X = "348" Y = "-174" T = "0" Pressure = "0" />
		<Point X = "354" Y = "-171" T = "0" Pressure = "0" />
		<Point X = "361" Y = "-165" T = "0" Pressure = "0" />
		<Point X = "370" Y = "-159" T = "0" Pressure = "0" />
		<Point X = "378" Y = "-152" T = "0" Pressure = "0" />
		<Point X = "378" Y = "-152" T = "0" Pressure = "0" />
		<Point X = "387" Y = "-144" T = "0" Pressure = "0" />
		<Point X = "396" Y = "-135" T = "0" Pressure = "0" />
		<Point X = "405" Y = "-129" T = "0" Pressure = "0" />
		<Point X = "414" Y = "-122" T = "0" Pressure = "0" />
		<Point X = "424" Y = "-117" T = "0" Pressure = "0" />
		<Point X = "424" Y = "-117" T = "0" Pressure = "0" />
		<Point X = "435" Y = "-113" T = "0" Pressure = "0" />
		<Point X = "445" Y = "-110" T = "0" Pressure = "0" />
		<Point X = "456" Y = "-110" T = "0" Pressure = "0" />
		<Point X = "456" Y = "-110" T = "0" Pressure = "0" />
		<Point X = "465" Y = "-110" T = "0" Pressure = "0" />
		<Point X = "471" Y = "-110" T = "0" Pressure = "0" />
		<Point X = "475" Y = "-110" T = "0" Pressure = "0" />
		<Point X = "475" Y = "-110" T = "0" Pressure = "0" />
		<Point X = "475" Y = "-110" T = "0" Pressure = "0" />
		<Point X = "475" Y = "-110" T = "0" Pressure = "0" />
	</Stroke>
</Gesture>
